<?xml version="1.0" encoding="utf-8"?>
<!DOCTYPE hibernate-mapping PUBLIC "-//Hibernate/Hibernate Mapping DTD 3.0//EN"
"http://www.hibernate.org/dtd/hibernate-mapping-3.0.dtd">
<!-- 
    Mapping file autogenerated by MyEclipse Persistence Tools
-->
<hibernate-mapping>
    <class name="com.bbs.bean.UserInfo" table="user_info" catalog="bbs">
        <id name="UId" type="java.lang.Integer">
            <column name="u_id" />
            <generator class="increment" />
        </id>
        <many-to-one name="role" class="com.bbs.bean.Role" fetch="select">
            <column name="r_id" />
        </many-to-one>
        <many-to-one name="question" class="com.bbs.bean.Question" fetch="select">
            <column name="q_id" />
        </many-to-one>
        <property name="UName" type="java.lang.String">
            <column name="u_name" length="30" />
        </property>
        <property name="UPwd" type="java.lang.String">
            <column name="u_pwd" length="16" />
        </property>
        <property name="UGender" type="java.lang.String">
            <column name="u_gender" length="2" />
        </property>
        <property name="UBirthday" type="java.sql.Timestamp">
            <column name="u_birthday" length="19" />
        </property>
        <property name="UPhone" type="java.lang.String">
            <column name="u_phone" length="11" />
        </property>
        <property name="UEmail" type="java.lang.String">
            <column name="u_email" length="30" />
        </property>
        <property name="UAddr" type="java.lang.String">
            <column name="u_addr" length="100" />
        </property>
        <property name="UFace" type="java.lang.String">
            <column name="u_face" length="100" />
        </property>
        <property name="USign" type="java.lang.String">
            <column name="u_sign" length="50" />
        </property>
        <property name="UCreatetimes" type="java.sql.Timestamp">
            <column name="u_createtimes" length="19" />
        </property>
        <property name="UAnswer" type="java.lang.String">
            <column name="u_answer" length="20" />
        </property>
        <property name="ULastLogintime" type="java.sql.Timestamp">
            <column name="u_lastLogintime" length="19" />
        </property>
        <property name="ULevel" type="java.lang.Integer">
            <column name="u_level" />
        </property>
        <property name="UCredit" type="java.lang.Integer">
            <column name="u_credit" />
        </property>
        <property name="UAddtime" type="java.sql.Timestamp">
            <column name="u_addtime" length="19" />
        </property>
        <property name="UFlag" type="java.lang.Integer">
            <column name="u_flag" />
        </property>
        <property name="UActiveCode" type="java.lang.String">
            <column name="u_activeCode" length="32" />
        </property>
        <property name="UState" type="java.lang.Integer">
            <column name="u_state" />
        </property>
        <set name="friendsForFriUsermasterid" inverse="true">
            <key>
                <column name="fri_usermasterid" />
            </key>
            <one-to-many class="com.bbs.bean.Friend" />
        </set>
        <set name="attentionsForAUsermasterid" inverse="true">
            <key>
                <column name="a_usermasterid" />
            </key>
            <one-to-many class="com.bbs.bean.Attention" />
        </set>
        <set name="friendsForFriUserslavesid" inverse="true">
            <key>
                <column name="fri_userslavesid" />
            </key>
            <one-to-many class="com.bbs.bean.Friend" />
        </set>
        <set name="attentionsForAUserslavesid" inverse="true">
            <key>
                <column name="a_userslavesid" />
            </key>
            <one-to-many class="com.bbs.bean.Attention" />
        </set>
        <set name="favorites" inverse="true">
            <key>
                <column name="u_id" />
            </key>
            <one-to-many class="com.bbs.bean.Favorite" />
        </set>
        <set name="forums" inverse="true">
            <key>
                <column name="u_id" />
            </key>
            <one-to-many class="com.bbs.bean.Forum" />
        </set>
    </class>
</hibernate-mapping>
